neshan/__init__.py
neshan/client.py
neshan/convert.py
neshan/directions.py
neshan/distance_matrix.py
neshan/exceptions.py
neshan/geocoding.py
neshan/maps.py
neshan/places.py
neshan/roads.py
neshan-1.1.1.dist-info/AUTHORS
neshan-1.1.1.dist-info/LICENSE
neshan-1.1.1.dist-info/METADATA
neshan-1.1.1.dist-info/WHEEL
neshan-1.1.1.dist-info/top_level.txt
neshan-1.1.1.dist-info/RECORD
