Metadata-Version: 2.1
Name: neshan
Version: 1.1.1
Summary: Python client library for Neshan maps
Home-page: https://github.com/nshayanfar/neshan-services-python
Author: Nima Shayanfar
License: Apache 2.0
Platform: Posix; MacOS X; Windows
Classifier: Development Status :: 4 - Beta
Classifier: Intended Audience :: Developers
Classifier: License :: OSI Approved :: Apache Software License
Classifier: Operating System :: OS Independent
Classifier: Programming Language :: Python :: 3.5
Classifier: Programming Language :: Python :: 3.6
Classifier: Programming Language :: Python :: 3.7
Classifier: Programming Language :: Python :: 3.8
Classifier: Topic :: Internet
Requires-Python: >=3.5
Requires-Dist: requests (<3.0,>=2.20.0)
